CODEOWNERS
LICENSE
MANIFEST.in
README.md
environment.yml
setup.py
Semi_ATE/__init__.py
Semi_ATE/STDF/ASR.py
Semi_ATE/STDF/ATR.py
Semi_ATE/STDF/BPS.py
Semi_ATE/STDF/BSR.py
Semi_ATE/STDF/CDR.py
Semi_ATE/STDF/CNR.py
Semi_ATE/STDF/DTO.py
Semi_ATE/STDF/DTR.py
Semi_ATE/STDF/EPS.py
Semi_ATE/STDF/FAR.py
Semi_ATE/STDF/FSR.py
Semi_ATE/STDF/FTR.py
Semi_ATE/STDF/GDR.py
Semi_ATE/STDF/HBR.py
Semi_ATE/STDF/IDR.py
Semi_ATE/STDF/MCR.py
Semi_ATE/STDF/MIR.py
Semi_ATE/STDF/MMR.py
Semi_ATE/STDF/MPR.py
Semi_ATE/STDF/MRR.py
Semi_ATE/STDF/MSR.py
Semi_ATE/STDF/MTR.py
Semi_ATE/STDF/NMR.py
Semi_ATE/STDF/PCR.py
Semi_ATE/STDF/PGR.py
Semi_ATE/STDF/PIR.py
Semi_ATE/STDF/PLR.py
Semi_ATE/STDF/PMR.py
Semi_ATE/STDF/PRR.py
Semi_ATE/STDF/PSR.py
Semi_ATE/STDF/PTR.py
Semi_ATE/STDF/RDR.py
Semi_ATE/STDF/README.md
Semi_ATE/STDF/SBR.py
Semi_ATE/STDF/SDR.py
Semi_ATE/STDF/SSR.py
Semi_ATE/STDF/STDFFile.py
Semi_ATE/STDF/STDR.py
Semi_ATE/STDF/STR.py
Semi_ATE/STDF/TSR.py
Semi_ATE/STDF/VUR.py
Semi_ATE/STDF/WCR.py
Semi_ATE/STDF/WIR.py
Semi_ATE/STDF/WRR.py
Semi_ATE/STDF/__init__.py
Semi_ATE/STDF/utils.py
Semi_ATE_STDF.egg-info/PKG-INFO
Semi_ATE_STDF.egg-info/SOURCES.txt
Semi_ATE_STDF.egg-info/dependency_links.txt
Semi_ATE_STDF.egg-info/requires.txt
Semi_ATE_STDF.egg-info/top_level.txt
requirements/run.txt
requirements/test.txt