Metadata-Version: 2.1
Name: Semi-ATE-STDF
Version: 0.1.28
Summary: Library to read/write STDF/ATDF files
Home-page: https://github.com/Semi-ATE/STDF
Author: Tom Hören
Maintainer: Semi-ATE
Maintainer-email: info@Semi-ATE.com
License: MIT
Keywords: Semiconductor ATE Automatic Test Equipment STDF
Platform: Windows
Platform: Linux
Platform: Mac OS-X
Classifier: License :: OSI Approved :: MIT License
Classifier: Operating System :: MacOS
Classifier: Operating System :: Microsoft :: Windows
Classifier: Operating System :: POSIX :: Linux
Classifier: Programming Language :: Python :: 3 :: Only
Classifier: Programming Language :: Python :: 3.7
Classifier: Programming Language :: Python :: 3.8
Classifier: Programming Language :: Python :: 3.9
Classifier: Development Status :: 3 - Alpha
Classifier: Intended Audience :: Education
Classifier: Intended Audience :: Science/Research
Classifier: Intended Audience :: Developers
Classifier: Topic :: Software Development :: Libraries :: Python Modules
Classifier: Topic :: Scientific/Engineering
Classifier: Topic :: Scientific/Engineering :: Electronic Design Automation (EDA)
Classifier: Topic :: Scientific/Engineering :: Interface Engine/Protocol Translator
